cat_cafe/__init__.py
cat_cafe-0.0.1a0.dist-info/METADATA
cat_cafe-0.0.1a0.dist-info/WHEEL
cat_cafe-0.0.1a0.dist-info/RECORD
