Metadata-Version: 2.4
Name: cat-cafe
Version: 0.0.1a0
Summary: Continuous Alignment Testing Platform - LLM Observability and Testing Framework (Placeholder Package)
Project-URL: Homepage, https://github.com/thisisartium/cat-cafe
Project-URL: Documentation, https://docs.cat-cafe.ai
Project-URL: Repository, https://github.com/thisisartium/cat-cafe
Project-URL: Issues, https://github.com/thisisartium/cat-cafe/issues
Author-email: CAT Cafe Team <team@cat-cafe.ai>
Maintainer-email: CAT Cafe Team <team@cat-cafe.ai>
License: Apache-2.0
Keywords: ai,llm,ml,observability,opentelemetry,placeholder,testing,tracing
Classifier: Development Status :: 1 - Planning
Classifier: Framework :: FastAPI
Classifier: Intended Audience :: Developers
Classifier: License :: OSI Approved :: Apache Software License
Classifier: Programming Language :: Python :: 3
Classifier: Programming Language :: Python :: 3.12
Classifier: Topic :: Software Development :: Libraries :: Python Modules
Classifier: Topic :: Software Development :: Testing
Classifier: Topic :: System :: Monitoring
Requires-Python: >=3.12
